mycalc/calculator.py
ryeong-0.0.1.dist-info/METADATA
ryeong-0.0.1.dist-info/WHEEL
ryeong-0.0.1.dist-info/top_level.txt
ryeong-0.0.1.dist-info/RECORD
