Metadata-Version: 2.1
Name: ryeong
Version: 0.0.1
Summary: nice calculator
Home-page: https://github.com/RYEONGRYEONG/mycalc.git
Download-URL: https://github.com/RYEONGRYEONG/mycalc.git
Author: seongryeong jo
License: UNKNOWN
Platform: UNKNOWN
Classifier: Programming Language :: Python :: 3
